{"excerpt":"","headers":[{"level":2,"title":"Mapping Logic In The Endpoint Class","slug":"mapping-logic-in-the-endpoint-class","children":[]},{"level":2,"title":"Mapping Logic In a Separate Class","slug":"mapping-logic-in-a-separate-class","children":[]}],"title":"Domain Entity Mapping","description":"A light-weight REST Api framework for ASP.Net 6 that implements REPR (Request-Endpoint-Response) Pattern.","frontmatter":{"title":"Domain Entity Mapping","description":"A light-weight REST Api framework for ASP.Net 6 that implements REPR (Request-Endpoint-Response) Pattern."},"lastUpdated":1658326564297}